json_validation_utils/__init__.py
json_validation_utils/console_helper.py
json_validation_utils/constants.py
json_validation_utils/file_utils.py
json_validation_utils/generate_json_schema.py
json_validation_utils/system_caller.py
json_validation_utils/validate_json_file.py
json_validation_utils-0.1.1.dist-info/AUTHORS.rst
json_validation_utils-0.1.1.dist-info/METADATA
json_validation_utils-0.1.1.dist-info/WHEEL
json_validation_utils-0.1.1.dist-info/entry_points.txt
json_validation_utils-0.1.1.dist-info/top_level.txt
json_validation_utils-0.1.1.dist-info/RECORD
