Metadata-Version: 2.2
Name: json_validation_utils
Version: 0.1.1
Summary: Collection of Python scripts for generating a JSON schema and performing JSON schema validation.
Home-page: https://github.com/jai-python3/json-validation-utils
Author: Jaideep Sundaram
Author-email: jai.python3@gmail.com
Keywords: json_validation_utils
Classifier: Development Status :: 5 - Production/Stable
Classifier: Intended Audience :: Developers
Classifier: Natural Language :: English
Classifier: Programming Language :: Python :: 3.10
Requires-Python: >=3.10
License-File: AUTHORS.rst
Requires-Dist: Click>=7.0
Requires-Dist: PyYAML
Requires-Dist: Rich
Requires-Dist: genson
Requires-Dist: jsonschema
Dynamic: author
Dynamic: author-email
Dynamic: classifier
Dynamic: description
Dynamic: home-page
Dynamic: keywords
Dynamic: requires-dist
Dynamic: requires-python
Dynamic: summary
